gmail_mcp_server/__init__.py
gmail_mcp_server/main.py
rickjang_gmail_mcp_server-1.1.0.dist-info/licenses/LICENSE
rickjang_gmail_mcp_server-1.1.0.dist-info/METADATA
rickjang_gmail_mcp_server-1.1.0.dist-info/WHEEL
rickjang_gmail_mcp_server-1.1.0.dist-info/entry_points.txt
rickjang_gmail_mcp_server-1.1.0.dist-info/top_level.txt
rickjang_gmail_mcp_server-1.1.0.dist-info/RECORD
