Metadata-Version: 2.4
Name: rickjang-gmail-mcp-server
Version: 1.1.0
Summary: A resilient MCP server built with fastMCP for sending emails through Gmail's SMTP server using AI agents via stdio transport
Author-email: Rick Jang <rickjang@example.com>
License-Expression: MIT
Project-URL: Homepage, https://github.com/rickjang/Gmail-mcp-server
Project-URL: Repository, https://github.com/rickjang/Gmail-mcp-server
Project-URL: Issues, https://github.com/rickjang/Gmail-mcp-server/issues
Keywords: mcp,gmail,email,smtp,ai,agent
Classifier: Development Status :: 4 - Beta
Classifier: Intended Audience :: Developers
Classifier: Programming Language :: Python :: 3
Classifier: Programming Language :: Python :: 3.10
Classifier: Programming Language :: Python :: 3.11
Classifier: Programming Language :: Python :: 3.12
Classifier: Topic :: Communications :: Email
Classifier: Topic :: Software Development :: Libraries :: Python Modules
Requires-Python: >=3.10
License-File: LICENSE
Requires-Dist: fastmcp
Requires-Dist: python-dotenv
Requires-Dist: requests
Dynamic: license-file
